copier_tools/EntryPoint.py
copier_tools/Math.py
copier_tools/__init__.py
copier_tools-0.1.2.dist-info/LICENSE.txt
copier_tools-0.1.2.dist-info/METADATA
copier_tools-0.1.2.dist-info/WHEEL
copier_tools-0.1.2.dist-info/top_level.txt
copier_tools-0.1.2.dist-info/RECORD
