Metadata-Version: 2.1
Name: copier_tools
Version: 0.1.2
Summary: Tools and functionality used when working with [copier](https://copier.readthedocs.io/).
Author-email: Scientific Software Engineering Center at Georgia Tech <sse-center@gatech.edu>
License: MIT
Project-URL: Homepage, https://github.com/gt-sse-center/copier_tools
Project-URL: Documentation, https://github.com/gt-sse-center/copier_tools
Project-URL: Repository, https://github.com/gt-sse-center/copier_tools
Classifier: License :: OSI Approved :: MIT License
Classifier: Operating System :: MacOS
Classifier: Operating System :: Microsoft :: Windows
Classifier: Operating System :: POSIX :: Linux
Classifier: Programming Language :: Python
Classifier: Programming Language :: Python :: 3.10
Classifier: Programming Language :: Python :: 3.11
Classifier: Programming Language :: Python :: 3.12
License-File: LICENSE.txt
Requires-Dist: typer ~=0.9
Provides-Extra: dev
Requires-Dist: copier ~=9.2 ; extra == 'dev'
Requires-Dist: dbrownell-DevTools ; extra == 'dev'
Provides-Extra: package
Requires-Dist: build ~=1.2 ; extra == 'package'
Requires-Dist: cx-Freeze ~=6.15 ; extra == 'package'
Requires-Dist: twine ~=4.0 ; extra == 'package'
